aries_staticagent/__init__.py
aries_staticagent/crypto.py
aries_staticagent/dispatcher.py
aries_staticagent/message.py
aries_staticagent/module.py
aries_staticagent/mtc.py
aries_staticagent/static_connection.py
aries_staticagent/type.py
aries_staticagent/utils.py
aries_staticagent-0.8.0.dist-info/LICENSE
aries_staticagent-0.8.0.dist-info/METADATA
aries_staticagent-0.8.0.dist-info/WHEEL
aries_staticagent-0.8.0.dist-info/top_level.txt
aries_staticagent-0.8.0.dist-info/RECORD
