Metadata-Version: 2.1
Name: aries-staticagent
Version: 0.8.0
Summary: Python Static Agent Library and Examples for Aries
Home-page: https://github.com/hyperledger/aries-staticagent-python
Author: Daniel Bluhm <daniel.bluhm@sovrin.org>, Sam Curren <sam@sovrin.org>
License: Apache 2.0
Platform: UNKNOWN
Classifier: Programming Language :: Python :: 3
Classifier: License :: OSI Approved :: Apache Software License
Classifier: Operating System :: OS Independent
Requires-Python: >=3.6
Requires-Dist: aiohttp
Requires-Dist: base58
Requires-Dist: msgpack
Requires-Dist: pynacl
Requires-Dist: semver
Requires-Dist: sortedcontainers
Provides-Extra: test
Requires-Dist: coverage ; extra == 'test'
Requires-Dist: flake8 ; extra == 'test'
Requires-Dist: pytest ; extra == 'test'
Requires-Dist: pytest-asyncio ; extra == 'test'
